{"mc":{
	"hand_ani":{
		"frameRate":24,
		"labels":[
			{"name":"hand_ani","frame":1,"end":15}
			
			],
		"events":[
			
			],
		"frames":[
			
			{
			"res":"781B54EB",
			"x":18,
			"y":47,
			"duration":3
			},
			{
			"res":"D2E55CCE",
			"x":18,
			"y":42,
			"duration":3
			},
			{
			"res":"F0803247",
			"x":18,
			"y":37,
			"duration":3
			},
			{
			"res":"249A1DE9",
			"x":18,
			"y":8,
			"duration":3
			},
			{
			"res":"CBD55177",
			"x":0,
			"y":8,
			"duration":3
			}
			]
}},
	"res":{
		"781B54EB":{"x":1,"y":119,"w":80,"h":87},
		"D2E55CCE":{"x":165,"y":119,"w":80,"h":87},
		"249A1DE9":{"x":103,"y":1,"w":82,"h":116},
		"F0803247":{"x":83,"y":119,"w":80,"h":87},
		"CBD55177":{"x":1,"y":1,"w":100,"h":116}
	}}